{
    "$schema": "http://schema.management.azure.com/schemas/2015-01-01/deploymentParameters.json#",
    "contentVersion": "1.0.0.0",
    "parameters": {
      "accountName": {
        "value": "kristianAutomationAccount"
      },
      "jobId": {
        "value": "102bab39-6745-4e43-89b2-84df4b01febf"
      },
      "credentialName": {
        "value": "kristianCredential"
      },
      "userName": {
        "value": "KristianShevandoTask9"
      },
      "password": {
        "value": "kYdzpUzvSEKOj/8lzvuY1R4Kk38z1vYshYxKxfngauk="
      }
    }
  }